AUTHORS.rst
CONTRIBUTING.rst
HISTORY.rst
LICENSE
MANIFEST.in
README.rst
setup.cfg
setup.py
docs/Makefile
docs/authors.rst
docs/conf.py
docs/contributing.rst
docs/history.rst
docs/index.rst
docs/installation.rst
docs/make.bat
docs/readme.rst
docs/usage.rst
pyfin/__init__.py
pyfin/option.py
pyfin_option.egg-info/PKG-INFO
pyfin_option.egg-info/SOURCES.txt
pyfin_option.egg-info/dependency_links.txt
pyfin_option.egg-info/not-zip-safe
pyfin_option.egg-info/top_level.txt
tests/__init__.py
tests/test_option.py